ISL/TP_Individual/Flip-flop_D/d_flip_flop.v
module d_flip_flop (
    input wire D,    // Entradas do flip-flop D
    input wire clk,  // Entradas do clock
    input wire reset,// Entradas de reset
    output reg Q     // Saída do flip-flop D
);

    // Bloco sempre sensível à borda do clock ou do reset
    always @(posedge clk or posedge reset) begin
        if (reset) begin
            Q <= 0;  // Se reset estiver ativo, zera a saída Q
        end else begin
            Q <= D;  // Se reset estiver desativado, a saída Q recebe o valor de D na borda do clock
        end
    end

endmodule

ISL/TP_Individual/Flip-flop_D/tb_d_flip_flop.v
module tb_d_flip_flop;

    reg D;         // Entrada D do flip-flop
    reg clk;       // Clock
    reg reset;     // Sinal de reset
    wire Q;        // Saída do Q do flip-flop

    // Módulo d_flip_flop
    d_flip_flop uut (
        .D(D),
        .clk(clk),
        .reset(reset),
        .Q(Q)
    );

    // Geração do clock
    initial begin
        clk = 0;                 // Inicializa o clock em 0
        forever #5 clk = ~clk;   // Inverte o clock a cada 5 unidades de tempo
    end

    // Casos de teste
    initial begin

        // Armazena os dados de simulação
        $dumpfile("d_flip_flop_tb.vcd");
        $dumpvars(0, tb_d_flip_flop);

        // Inicializa com reset ativo e entrada D em 0
        reset = 1;
        D = 0;
        #10;  // Espera 10 unidades de tempo

        // Desativa o reset e define D como 1
        reset = 0;
        D = 1;
        #10;  // Espera 10 unidades de tempo

        // Define D como 0
        D = 0;
        #10;  // Espera 10 unidades de tempo

        // Define D como 1
        D = 1;
        #10;  // Espera 10 unidades de tempo

        // Ativa o reset
        reset = 1;
        #10;  // Espera 10 unidades de tempo

        // Desativa o reset e define D como 0
        reset = 0;
        D = 0;
        #10;  // Espera 10 unidades de tempo

        // Termina a simulação
        $finish;
    end

endmodule

ISL/TP_Individual/Flip-flop_D/d_flip_flop_tb.vcd
$date
	Tue Jul 30 03:13:15 2024
$end
$version
	Icarus Verilog
$end
$timescale
	1s
$end
$scope module tb_d_flip_flop $end
$var wire 1 ! Q $end
$var reg 1 " D $end
$var reg 1 # clk $end
$var reg 1 $ reset $end
$scope module uut $end
$var wire 1 " D $end
$var wire 1 # clk $end
$var wire 1 $ reset $end
$var reg 1 ! Q $end
$upscope $end
$upscope $end
$enddefinitions $end
$comment Show the parameter values. $end
$dumpall
$end
#0
$dumpvars
1$
0#
0"
0!
$end
#5
1#
#10
0#
1"
0$
#15
1!
1#
#20
0#
0"
#25
0!
1#
#30
0#
1"
#35
1!
1#
#40
0!
0#
1$
#45
1#
#50
0#
0"
0$
